agbenchmark/README.md
agbenchmark/__init__.py
agbenchmark/__main__.py
agbenchmark/agent_api_interface.py
agbenchmark/agent_interface.py
agbenchmark/agent_protocol_client/__init__.py
agbenchmark/agent_protocol_client/api/__init__.py
agbenchmark/agent_protocol_client/api/agent_api.py
agbenchmark/agent_protocol_client/api_client.py
agbenchmark/agent_protocol_client/api_response.py
agbenchmark/agent_protocol_client/configuration.py
agbenchmark/agent_protocol_client/docs/AgentApi.md
agbenchmark/agent_protocol_client/exceptions.py
agbenchmark/agent_protocol_client/models/__init__.py
agbenchmark/agent_protocol_client/models/artifact.py
agbenchmark/agent_protocol_client/models/artifacts.py
agbenchmark/agent_protocol_client/models/pagination.py
agbenchmark/agent_protocol_client/models/step.py
agbenchmark/agent_protocol_client/models/step_all_of.py
agbenchmark/agent_protocol_client/models/step_request_body.py
agbenchmark/agent_protocol_client/models/step_result.py
agbenchmark/agent_protocol_client/models/task.py
agbenchmark/agent_protocol_client/models/task_all_of.py
agbenchmark/agent_protocol_client/models/task_request_body.py
agbenchmark/agent_protocol_client/rest.py
agbenchmark/app.py
agbenchmark/challenges/CHALLENGE.md
agbenchmark/challenges/README.md
agbenchmark/challenges/__init__.py
agbenchmark/challenges/abilities/read_file/artifacts_in/file_to_read.txt
agbenchmark/challenges/abilities/read_file/artifacts_out/file_to_check.txt
agbenchmark/challenges/abilities/read_file/artifacts_out/output.txt
agbenchmark/challenges/abilities/read_file/data.json
agbenchmark/challenges/abilities/write_file/artifacts_out/random_file.txt
agbenchmark/challenges/abilities/write_file/data.json
agbenchmark/challenges/alignment/1_distraction/artifacts_in/instructions.txt
agbenchmark/challenges/alignment/1_distraction/artifacts_out/goal.txt
agbenchmark/challenges/alignment/1_distraction/data.json
agbenchmark/challenges/alignment/2_injection/artifacts_in/instructions.txt
agbenchmark-0.0.10.dist-info/LICENSE
agbenchmark-0.0.10.dist-info/METADATA
agbenchmark-0.0.10.dist-info/WHEEL
agbenchmark-0.0.10.dist-info/entry_points.txt
agbenchmark-0.0.10.dist-info/RECORD
