Metadata-Version: 2.1
Name: agbenchmark
Version: 0.0.10
Summary: Benchmarking the performance of agents far and wide, regardless of how they are set up and how they work
License: MIT
Author: Silen Naihin
Author-email: silen.naihin@gmail.com
Requires-Python: >=3.10,<4.0
Classifier: License :: OSI Approved :: MIT License
Classifier: Programming Language :: Python :: 3
Classifier: Programming Language :: Python :: 3.10
Classifier: Programming Language :: Python :: 3.11
Requires-Dist: click (>=8.1.3,<9.0.0)
Requires-Dist: colorama (>=0.4.6,<0.5.0)
Requires-Dist: fastapi (>=0.99.0,<0.100.0)
Requires-Dist: gitpython (>=3.1.32,<4.0.0)
Requires-Dist: helicone (>=1.0.9,<2.0.0)
Requires-Dist: matplotlib (>=3.7.2,<4.0.0)
Requires-Dist: networkx (>=3.1,<4.0)
Requires-Dist: openai (>=0.27.8,<0.28.0)
Requires-Dist: pandas (>=2.0.3,<3.0.0)
Requires-Dist: pexpect (>=4.8.0,<5.0.0)
Requires-Dist: psutil (>=5.9.5,<6.0.0)
Requires-Dist: pydantic (>=1.10.9,<2.0.0)
Requires-Dist: pytest (>=7.3.2,<8.0.0)
Requires-Dist: pytest-asyncio (>=0.21.1,<0.22.0)
Requires-Dist: python-dotenv (>=1.0.0,<2.0.0)
Requires-Dist: python-multipart (>=0.0.6,<0.0.7)
Requires-Dist: pyvis (>=0.3.2,<0.4.0)
Requires-Dist: requests (>=2.31.0,<3.0.0)
Requires-Dist: selenium (>=4.11.2,<5.0.0)
Requires-Dist: toml (>=0.10.2,<0.11.0)
Requires-Dist: types-requests (>=2.31.0.1,<3.0.0.0)
Requires-Dist: uvicorn (>=0.23.2,<0.24.0)
